quaternions/__init__.py
quaternions/quaternion.py
quaternions-0.6.dist-info/LICENSE.rst
quaternions-0.6.dist-info/METADATA
quaternions-0.6.dist-info/WHEEL
quaternions-0.6.dist-info/top_level.txt
quaternions-0.6.dist-info/RECORD
