Metadata-Version: 2.1
Name: quaternions
Version: 0.6
Summary: A package to handle quaternions
Home-page: https://github.com/mjsobrep/quaternions
Author: Michael Sobrepera
Author-email: mjsobrep@live.com
License: MIT
Keywords: quaternion transformations
Platform: UNKNOWN
Classifier: Development Status :: 3 - Alpha
Classifier: Intended Audience :: Science/Research
Classifier: License :: OSI Approved :: MIT License
Classifier: Natural Language :: English
Classifier: Operating System :: OS Independent
Classifier: Programming Language :: Python
License-File: LICENSE.rst
